pyearthtools/tutorial/ERA5DataClass.py
pyearthtools/tutorial/HadisdDataClass.py
pyearthtools/tutorial/__init__.py
pyearthtools/tutorial/ancilliary/ERA5lowres.py
pyearthtools/tutorial/ancilliary/__init__.py
pyearthtools/tutorial/structure/ERA5lowres.struc
pyearthtools/tutorial/structure/__init__.py
pyearthtools_tutorial-0.5.1.dist-info/METADATA
pyearthtools_tutorial-0.5.1.dist-info/WHEEL
pyearthtools_tutorial-0.5.1.dist-info/RECORD
