Metadata-Version: 2.4
Name: pyearthtools-tutorial
Version: 0.5.1
Dynamic: Description
Dynamic: Description-Content-Type
Summary: Tutorial material for PyEarthTools
Project-URL: homepage, https://pyearthtools.readthedocs.io/
Project-URL: documentation, https://pyearthtools.readthedocs.io/
Project-URL: repository, https://github.com/ACCESS-Community-Hub/PyEarthTools
Maintainer-email: Tennessee Leeuwenburg <tennessee.leeuwenburg@bom.gov.au>
Keywords: pyearthtools
Classifier: Operating System :: OS Independent
Classifier: Programming Language :: Python :: 3
Requires-Python: >=3.10
Requires-Dist: basemap
Requires-Dist: dask
Requires-Dist: gcsfs
Requires-Dist: hydra-core
Requires-Dist: ipykernel
Requires-Dist: ipywidgets
Requires-Dist: jupyterlab
Requires-Dist: pint-pandas
Requires-Dist: pint-xarray
Requires-Dist: plotly
Requires-Dist: pyearthtools-pipeline
Requires-Dist: pyearthtools-training
Requires-Dist: pyearthtools-utils
Requires-Dist: rich
Requires-Dist: scores
Requires-Dist: xgboost
